psll/__init__.py
psll/__main__.py
psll/ascii_trees.py
psll/build.py
psll/lexer.py
psll/macros.py
psll/optimisers.py
psll/preprocessor.py
psll-0.1.9.dist-info/entry_points.txt
psll-0.1.9.dist-info/licenses/LICENSE
psll-0.1.9.dist-info/WHEEL
psll-0.1.9.dist-info/METADATA
psll-0.1.9.dist-info/RECORD
