Metadata-Version: 2.4
Name: psll
Version: 0.1.9
Summary: Macro-driven metalanguage which compiles to Pyramid Scheme.
Keywords: compiler,macros,code-golf,pyramid-scheme,programming-language
Author-email: Marcin Konowalczyk <marcin.konow@lczyk.xyz>
Requires-Python: >=3.9
Classifier: License :: OSI Approved :: MIT License
Classifier: Programming Language :: Python
Classifier: Programming Language :: Python :: 3.9
Classifier: Programming Language :: Other
Classifier: Development Status :: 3 - Alpha
Classifier: Environment :: Console
License-File: LICENSE
Requires-Dist: more-itertools>=8.5.0
Project-URL: Homepage, https://github.com/MarcinKonowalczyk/psll-lang
